{
  "id": "00000000-0000-0000-0000-000000000000",
  "prevId": "",
  "version": "7",
  "dialect": "postgresql",
  "tables": {
    "public.usuarios": {
      "name": "usuarios",
      "schema": "",
      "columns": {
        "id": {
          "name": "id",
          "type": "serial",
          "primaryKey": true,
          "notNull": true
        },
        "nome_completo": {
          "name": "nome_completo",
          "type": "text",
          "primaryKey": false,
          "notNull": true
        },
        "login": {
          "name": "login",
          "type": "varchar(100)",
          "primaryKey": false,
          "notNull": false
        },
        "senha": {
          "name": "senha",
          "type": "text",
          "primaryKey": false,
          "notNull": true
        },
        "perfil": {
          "name": "perfil",
          "type": "varchar(50)",
          "primaryKey": false,
          "notNull": true,
          "default": "'Professor'"
        },
        "genero": {
          "name": "genero",
          "type": "varchar(1)",
          "primaryKey": false,
          "notNull": false
        }
      },
      "indexes": {},
      "foreignKeys": {},
      "compositePrimaryKeys": {},
      "uniqueConstraints": {
        "usuarios_login_unique": {
          "columns": [
            "login"
          ],
          "nullsNotDistinct": false,
          "name": "usuarios_login_unique"
        }
      },
      "checkConstraints": {},
      "policies": {},
      "isRLSEnabled": false
    },
    "public.turmas": {
      "name": "turmas",
      "schema": "",
      "columns": {
        "id": {
          "name": "id",
          "type": "serial",
          "primaryKey": true,
          "notNull": true
        },
        "nome_turma": {
          "name": "nome_turma",
          "type": "varchar(50)",
          "primaryKey": false,
          "notNull": true
        },
        "turno": {
          "name": "turno",
          "type": "varchar(20)",
          "primaryKey": false,
          "notNull": false
        },
        "professor_responsavel": {
          "name": "professor_responsavel",
          "type": "text",
          "primaryKey": false,
          "notNull": false
        },
        "prof_complementador": {
          "name": "prof_complementador",
          "type": "text",
          "primaryKey": false,
          "notNull": false
        },
        "prof_educacao_fisica": {
          "name": "prof_educacao_fisica",
          "type": "text",
          "primaryKey": false,
          "notNull": false
        },
        "auxiliar_turma": {
          "name": "auxiliar_turma",
          "type": "text",
          "primaryKey": false,
          "notNull": false
        },
        "cor": {
          "name": "cor",
          "type": "varchar(30)",
          "primaryKey": false,
          "notNull": false,
          "default": "'#3b82f6'"
        }
      },
      "indexes": {},
      "foreignKeys": {},
      "compositePrimaryKeys": {},
      "uniqueConstraints": {},
      "checkConstraints": {},
      "policies": {},
      "isRLSEnabled": false
    },
    "public.professores": {
      "name": "professores",
      "schema": "",
      "columns": {
        "id": {
          "name": "id",
          "type": "serial",
          "primaryKey": true,
          "notNull": true
        },
        "nome": {
          "name": "nome",
          "type": "text",
          "primaryKey": false,
          "notNull": true
        },
        "cpf": {
          "name": "cpf",
          "type": "varchar(20)",
          "primaryKey": false,
          "notNull": false
        },
        "matricula": {
          "name": "matricula",
          "type": "varchar(30)",
          "primaryKey": false,
          "notNull": false
        },
        "turma_manha": {
          "name": "turma_manha",
          "type": "varchar(20)",
          "primaryKey": false,
          "notNull": false
        },
        "turma_tarde": {
          "name": "turma_tarde",
          "type": "varchar(20)",
          "primaryKey": false,
          "notNull": false
        },
        "turno": {
          "name": "turno",
          "type": "varchar(20)",
          "primaryKey": false,
          "notNull": false
        },
        "telefone": {
          "name": "telefone",
          "type": "varchar(30)",
          "primaryKey": false,
          "notNull": false
        },
        "vinculo": {
          "name": "vinculo",
          "type": "varchar(100)",
          "primaryKey": false,
          "notNull": false
        },
        "email": {
          "name": "email",
          "type": "text",
          "primaryKey": false,
          "notNull": false
        },
        "identificacao_censo": {
          "name": "identificacao_censo",
          "type": "varchar(30)",
          "primaryKey": false,
          "notNull": false
        },
        "data_nascimento": {
          "name": "data_nascimento",
          "type": "varchar(20)",
          "primaryKey": false,
          "notNull": false
        },
        "foto": {
          "name": "foto",
          "type": "text",
          "primaryKey": false,
          "notNull": false
        },
        "cargo": {
          "name": "cargo",
          "type": "varchar(100)",
          "primaryKey": false,
          "notNull": false
        },
        "jornada": {
          "name": "jornada",
          "type": "varchar(50)",
          "primaryKey": false,
          "notNull": false
        },
        "titulacao": {
          "name": "titulacao",
          "type": "varchar(50)",
          "primaryKey": false,
          "notNull": false
        }
      },
      "indexes": {},
      "foreignKeys": {},
      "compositePrimaryKeys": {},
      "uniqueConstraints": {
        "professores_matricula_unique": {
          "columns": [
            "matricula"
          ],
          "nullsNotDistinct": false,
          "name": "professores_matricula_unique"
        }
      },
      "checkConstraints": {},
      "policies": {},
      "isRLSEnabled": false
    },
    "public.funcionarios": {
      "name": "funcionarios",
      "schema": "",
      "columns": {
        "id": {
          "name": "id",
          "type": "serial",
          "primaryKey": true,
          "notNull": true
        },
        "nome_completo": {
          "name": "nome_completo",
          "type": "text",
          "primaryKey": false,
          "notNull": true
        },
        "cpf": {
          "name": "cpf",
          "type": "varchar(20)",
          "primaryKey": false,
          "notNull": false
        },
        "matricula": {
          "name": "matricula",
          "type": "varchar(20)",
          "primaryKey": false,
          "notNull": false
        },
        "funcao": {
          "name": "funcao",
          "type": "varchar(100)",
          "primaryKey": false,
          "notNull": false
        },
        "turno": {
          "name": "turno",
          "type": "varchar(20)",
          "primaryKey": false,
          "notNull": false
        },
        "telefone_contato": {
          "name": "telefone_contato",
          "type": "varchar(30)",
          "primaryKey": false,
          "notNull": false
        },
        "contato_emergencia": {
          "name": "contato_emergencia",
          "type": "varchar(30)",
          "primaryKey": false,
          "notNull": false
        },
        "data_admissao": {
          "name": "data_admissao",
          "type": "varchar(20)",
          "primaryKey": false,
          "notNull": false
        },
        "vinculo": {
          "name": "vinculo",
          "type": "varchar(50)",
          "primaryKey": false,
          "notNull": false
        },
        "status": {
          "name": "status",
          "type": "varchar(20)",
          "primaryKey": false,
          "notNull": false,
          "default": "'Ativo'"
        },
        "foto": {
          "name": "foto",
          "type": "text",
          "primaryKey": false,
          "notNull": false
        }
      },
      "indexes": {},
      "foreignKeys": {},
      "compositePrimaryKeys": {},
      "uniqueConstraints": {},
      "checkConstraints": {},
      "policies": {},
      "isRLSEnabled": false
    },
    "public.impressoes": {
      "name": "impressoes",
      "schema": "",
      "columns": {
        "id": {
          "name": "id",
          "type": "serial",
          "primaryKey": true,
          "notNull": true
        },
        "data_pedido": {
          "name": "data_pedido",
          "type": "timestamp",
          "primaryKey": false,
          "notNull": false,
          "default": "now()"
        },
        "professor_solicitante": {
          "name": "professor_solicitante",
          "type": "text",
          "primaryKey": false,
          "notNull": true
        },
        "link_arquivo": {
          "name": "link_arquivo",
          "type": "text",
          "primaryKey": false,
          "notNull": true
        },
        "nome_arquivo": {
          "name": "nome_arquivo",
          "type": "text",
          "primaryKey": false,
          "notNull": false
        },
        "tipo_arquivo": {
          "name": "tipo_arquivo",
          "type": "varchar(50)",
          "primaryKey": false,
          "notNull": false
        },
        "observacoes": {
          "name": "observacoes",
          "type": "text",
          "primaryKey": false,
          "notNull": false
        },
        "quantidade_copias": {
          "name": "quantidade_copias",
          "type": "integer",
          "primaryKey": false,
          "notNull": true,
          "default": 1
        },
        "duplex": {
          "name": "duplex",
          "type": "boolean",
          "primaryKey": false,
          "notNull": false,
          "default": false
        },
        "data_para_uso": {
          "name": "data_para_uso",
          "type": "varchar(30)",
          "primaryKey": false,
          "notNull": false
        },
        "horario_impressao": {
          "name": "horario_impressao",
          "type": "varchar(10)",
          "primaryKey": false,
          "notNull": false
        },
        "status": {
          "name": "status",
          "type": "varchar(20)",
          "primaryKey": false,
          "notNull": true,
          "default": "'Pendente'"
        },
        "lido": {
          "name": "lido",
          "type": "boolean",
          "primaryKey": false,
          "notNull": false,
          "default": false
        },
        "imprimiu_em": {
          "name": "imprimiu_em",
          "type": "timestamp",
          "primaryKey": false,
          "notNull": false
        }
      },
      "indexes": {},
      "foreignKeys": {},
      "compositePrimaryKeys": {},
      "uniqueConstraints": {},
      "checkConstraints": {},
      "policies": {},
      "isRLSEnabled": false
    },
    "public.alertas": {
      "name": "alertas",
      "schema": "",
      "columns": {
        "id": {
          "name": "id",
          "type": "serial",
          "primaryKey": true,
          "notNull": true
        },
        "tipo": {
          "name": "tipo",
          "type": "varchar(50)",
          "primaryKey": false,
          "notNull": true
        },
        "mensagem": {
          "name": "mensagem",
          "type": "text",
          "primaryKey": false,
          "notNull": true
        },
        "criado_em": {
          "name": "criado_em",
          "type": "timestamp",
          "primaryKey": false,
          "notNull": false,
          "default": "now()"
        },
        "lido": {
          "name": "lido",
          "type": "boolean",
          "primaryKey": false,
          "notNull": false,
          "default": false
        },
        "dados": {
          "name": "dados",
          "type": "jsonb",
          "primaryKey": false,
          "notNull": false
        }
      },
      "indexes": {},
      "foreignKeys": {},
      "compositePrimaryKeys": {},
      "uniqueConstraints": {},
      "checkConstraints": {},
      "policies": {},
      "isRLSEnabled": false
    },
    "public.alunos": {
      "name": "alunos",
      "schema": "",
      "columns": {
        "id": {
          "name": "id",
          "type": "serial",
          "primaryKey": true,
          "notNull": true
        },
        "matricula": {
          "name": "matricula",
          "type": "varchar(50)",
          "primaryKey": false,
          "notNull": false
        },
        "nome_completo": {
          "name": "nome_completo",
          "type": "text",
          "primaryKey": false,
          "notNull": true
        },
        "data_nascimento": {
          "name": "data_nascimento",
          "type": "varchar(30)",
          "primaryKey": false,
          "notNull": false
        },
        "turma_atual": {
          "name": "turma_atual",
          "type": "varchar(50)",
          "primaryKey": false,
          "notNull": false
        },
        "turno": {
          "name": "turno",
          "type": "varchar(20)",
          "primaryKey": false,
          "notNull": false
        },
        "nome_mae": {
          "name": "nome_mae",
          "type": "text",
          "primaryKey": false,
          "notNull": false
        },
        "nome_pai": {
          "name": "nome_pai",
          "type": "text",
          "primaryKey": false,
          "notNull": false
        },
        "responsavel": {
          "name": "responsavel",
          "type": "text",
          "primaryKey": false,
          "notNull": false
        },
        "telefone": {
          "name": "telefone",
          "type": "text",
          "primaryKey": false,
          "notNull": false
        },
        "email_pessoal": {
          "name": "email_pessoal",
          "type": "text",
          "primaryKey": false,
          "notNull": false
        },
        "email_responsavel": {
          "name": "email_responsavel",
          "type": "text",
          "primaryKey": false,
          "notNull": false
        },
        "endereco": {
          "name": "endereco",
          "type": "text",
          "primaryKey": false,
          "notNull": false
        },
        "situacao": {
          "name": "situacao",
          "type": "varchar(50)",
          "primaryKey": false,
          "notNull": false
        },
        "sexo": {
          "name": "sexo",
          "type": "varchar(1)",
          "primaryKey": false,
          "notNull": false
        },
        "etnia": {
          "name": "etnia",
          "type": "varchar(50)",
          "primaryKey": false,
          "notNull": false
        },
        "ano_ingresso": {
          "name": "ano_ingresso",
          "type": "varchar(10)",
          "primaryKey": false,
          "notNull": false
        },
        "nivel_ensino": {
          "name": "nivel_ensino",
          "type": "text",
          "primaryKey": false,
          "notNull": false
        },
        "descricao_curso": {
          "name": "descricao_curso",
          "type": "text",
          "primaryKey": false,
          "notNull": false
        },
        "zona_residencial": {
          "name": "zona_residencial",
          "type": "varchar(20)",
          "primaryKey": false,
          "notNull": false
        },
        "cpf": {
          "name": "cpf",
          "type": "varchar(20)",
          "primaryKey": false,
          "notNull": false
        },
        "cpf_responsavel": {
          "name": "cpf_responsavel",
          "type": "varchar(20)",
          "primaryKey": false,
          "notNull": false
        },
        "rg": {
          "name": "rg",
          "type": "text",
          "primaryKey": false,
          "notNull": false
        },
        "chave_responsavel": {
          "name": "chave_responsavel",
          "type": "varchar(20)",
          "primaryKey": false,
          "notNull": false
        },
        "email_google_classroom": {
          "name": "email_google_classroom",
          "type": "text",
          "primaryKey": false,
          "notNull": false
        },
        "ano_previsao_conclusao": {
          "name": "ano_previsao_conclusao",
          "type": "varchar(10)",
          "primaryKey": false,
          "notNull": false
        },
        "codigo_curso": {
          "name": "codigo_curso",
          "type": "varchar(20)",
          "primaryKey": false,
          "notNull": false
        },
        "arquivo_morto": {
          "name": "arquivo_morto",
          "type": "integer",
          "primaryKey": false,
          "notNull": false,
          "default": 0
        },
        "motivo_saida": {
          "name": "motivo_saida",
          "type": "text",
          "primaryKey": false,
          "notNull": false
        },
        "data_saida": {
          "name": "data_saida",
          "type": "varchar(30)",
          "primaryKey": false,
          "notNull": false
        },
        "data_transferencia": {
          "name": "data_transferencia",
          "type": "varchar(30)",
          "primaryKey": false,
          "notNull": false
        },
        "tipo_transferencia": {
          "name": "tipo_transferencia",
          "type": "varchar(20)",
          "primaryKey": false,
          "notNull": false
        },
        "turma_destino": {
          "name": "turma_destino",
          "type": "varchar(50)",
          "primaryKey": false,
          "notNull": false
        },
        "turma_origem": {
          "name": "turma_origem",
          "type": "varchar(50)",
          "primaryKey": false,
          "notNull": false
        },
        "naturalidade": {
          "name": "naturalidade",
          "type": "varchar(120)",
          "primaryKey": false,
          "notNull": false
        }
      },
      "indexes": {},
      "foreignKeys": {},
      "compositePrimaryKeys": {},
      "uniqueConstraints": {
        "alunos_matricula_unique": {
          "columns": [
            "matricula"
          ],
          "nullsNotDistinct": false,
          "name": "alunos_matricula_unique"
        }
      },
      "checkConstraints": {},
      "policies": {},
      "isRLSEnabled": false
    },
    "public.sync_status": {
      "name": "sync_status",
      "schema": "",
      "columns": {
        "id": {
          "name": "id",
          "type": "serial",
          "primaryKey": true,
          "notNull": true
        },
        "ultima_sync": {
          "name": "ultima_sync",
          "type": "timestamp",
          "primaryKey": false,
          "notNull": false
        },
        "status": {
          "name": "status",
          "type": "varchar(20)",
          "primaryKey": false,
          "notNull": true,
          "default": "'idle'"
        },
        "mensagem": {
          "name": "mensagem",
          "type": "text",
          "primaryKey": false,
          "notNull": false
        },
        "total_alunos": {
          "name": "total_alunos",
          "type": "text",
          "primaryKey": false,
          "notNull": false
        },
        "total_registros": {
          "name": "total_registros",
          "type": "text",
          "primaryKey": false,
          "notNull": false
        }
      },
      "indexes": {},
      "foreignKeys": {},
      "compositePrimaryKeys": {},
      "uniqueConstraints": {},
      "checkConstraints": {},
      "policies": {},
      "isRLSEnabled": false
    },
    "public.notas": {
      "name": "notas",
      "schema": "",
      "columns": {
        "id": {
          "name": "id",
          "type": "serial",
          "primaryKey": true,
          "notNull": true
        },
        "aluno_id": {
          "name": "aluno_id",
          "type": "integer",
          "primaryKey": false,
          "notNull": false
        },
        "bimestre": {
          "name": "bimestre",
          "type": "integer",
          "primaryKey": false,
          "notNull": false
        },
        "disciplina": {
          "name": "disciplina",
          "type": "varchar(100)",
          "primaryKey": false,
          "notNull": false
        },
        "nota_1": {
          "name": "nota_1",
          "type": "numeric(5, 2)",
          "primaryKey": false,
          "notNull": false
        },
        "nota_2": {
          "name": "nota_2",
          "type": "numeric(5, 2)",
          "primaryKey": false,
          "notNull": false
        },
        "nota_final": {
          "name": "nota_final",
          "type": "numeric(5, 2)",
          "primaryKey": false,
          "notNull": false
        },
        "media_final": {
          "name": "media_final",
          "type": "numeric(5, 2)",
          "primaryKey": false,
          "notNull": false
        },
        "situacao": {
          "name": "situacao",
          "type": "varchar(30)",
          "primaryKey": false,
          "notNull": false
        },
        "data_atualizacao": {
          "name": "data_atualizacao",
          "type": "timestamp",
          "primaryKey": false,
          "notNull": false,
          "default": "now()"
        }
      },
      "indexes": {},
      "foreignKeys": {
        "notas_aluno_id_alunos_id_fk": {
          "name": "notas_aluno_id_alunos_id_fk",
          "tableFrom": "notas",
          "tableTo": "alunos",
          "schemaTo": "public",
          "columnsFrom": [
            "aluno_id"
          ],
          "columnsTo": [
            "id"
          ],
          "onDelete": "no action",
          "onUpdate": "no action"
        }
      },
      "compositePrimaryKeys": {},
      "uniqueConstraints": {},
      "checkConstraints": {},
      "policies": {},
      "isRLSEnabled": false
    },
    "public.arquivo_morto": {
      "name": "arquivo_morto",
      "schema": "",
      "columns": {
        "id": {
          "name": "id",
          "type": "serial",
          "primaryKey": true,
          "notNull": true
        },
        "nome_aluno": {
          "name": "nome_aluno",
          "type": "varchar(255)",
          "primaryKey": false,
          "notNull": true
        },
        "matricula": {
          "name": "matricula",
          "type": "varchar(50)",
          "primaryKey": false,
          "notNull": false
        },
        "ano_saida": {
          "name": "ano_saida",
          "type": "varchar(10)",
          "primaryKey": false,
          "notNull": false
        },
        "turma": {
          "name": "turma",
          "type": "varchar(50)",
          "primaryKey": false,
          "notNull": false
        },
        "observacoes": {
          "name": "observacoes",
          "type": "text",
          "primaryKey": false,
          "notNull": false
        },
        "criado_em": {
          "name": "criado_em",
          "type": "timestamp",
          "primaryKey": false,
          "notNull": false,
          "default": "now()"
        },
        "atualizado_em": {
          "name": "atualizado_em",
          "type": "timestamp",
          "primaryKey": false,
          "notNull": false,
          "default": "now()"
        }
      },
      "indexes": {},
      "foreignKeys": {},
      "compositePrimaryKeys": {},
      "uniqueConstraints": {},
      "checkConstraints": {},
      "policies": {},
      "isRLSEnabled": false
    },
    "public.logins_externos": {
      "name": "logins_externos",
      "schema": "",
      "columns": {
        "id": {
          "name": "id",
          "type": "serial",
          "primaryKey": true,
          "notNull": true
        },
        "nome_site": {
          "name": "nome_site",
          "type": "varchar(255)",
          "primaryKey": false,
          "notNull": true
        },
        "url": {
          "name": "url",
          "type": "text",
          "primaryKey": false,
          "notNull": false
        },
        "login": {
          "name": "login",
          "type": "varchar(255)",
          "primaryKey": false,
          "notNull": true
        },
        "senha": {
          "name": "senha",
          "type": "text",
          "primaryKey": false,
          "notNull": true
        },
        "descricao": {
          "name": "descricao",
          "type": "text",
          "primaryKey": false,
          "notNull": false
        },
        "criado_em": {
          "name": "criado_em",
          "type": "timestamp",
          "primaryKey": false,
          "notNull": false,
          "default": "now()"
        },
        "atualizado_em": {
          "name": "atualizado_em",
          "type": "timestamp",
          "primaryKey": false,
          "notNull": false,
          "default": "now()"
        }
      },
      "indexes": {},
      "foreignKeys": {},
      "compositePrimaryKeys": {},
      "uniqueConstraints": {},
      "checkConstraints": {},
      "policies": {},
      "isRLSEnabled": false
    },
    "public.diario_configuracoes": {
      "name": "diario_configuracoes",
      "schema": "",
      "columns": {
        "id": {
          "name": "id",
          "type": "serial",
          "primaryKey": true,
          "notNull": true
        },
        "chave": {
          "name": "chave",
          "type": "varchar(100)",
          "primaryKey": false,
          "notNull": true
        },
        "valor": {
          "name": "valor",
          "type": "text",
          "primaryKey": false,
          "notNull": true
        }
      },
      "indexes": {},
      "foreignKeys": {},
      "compositePrimaryKeys": {},
      "uniqueConstraints": {
        "diario_configuracoes_chave_unique": {
          "columns": [
            "chave"
          ],
          "nullsNotDistinct": false,
          "name": "diario_configuracoes_chave_unique"
        }
      },
      "checkConstraints": {},
      "policies": {},
      "isRLSEnabled": false
    },
    "public.configuracoes": {
      "name": "configuracoes",
      "schema": "",
      "columns": {
        "id": {
          "name": "id",
          "type": "serial",
          "primaryKey": true,
          "notNull": true
        },
        "chave": {
          "name": "chave",
          "type": "varchar(100)",
          "primaryKey": false,
          "notNull": true
        },
        "valor": {
          "name": "valor",
          "type": "text",
          "primaryKey": false,
          "notNull": false
        },
        "atualizado_em": {
          "name": "atualizado_em",
          "type": "timestamp",
          "primaryKey": false,
          "notNull": false,
          "default": "now()"
        }
      },
      "indexes": {},
      "foreignKeys": {},
      "compositePrimaryKeys": {},
      "uniqueConstraints": {
        "configuracoes_chave_unique": {
          "columns": [
            "chave"
          ],
          "nullsNotDistinct": false,
          "name": "configuracoes_chave_unique"
        }
      },
      "checkConstraints": {},
      "policies": {},
      "isRLSEnabled": false
    },
    "public.presencas": {
      "name": "presencas",
      "schema": "",
      "columns": {
        "id": {
          "name": "id",
          "type": "serial",
          "primaryKey": true,
          "notNull": true
        },
        "aluno_id": {
          "name": "aluno_id",
          "type": "integer",
          "primaryKey": false,
          "notNull": false
        },
        "bimestre": {
          "name": "bimestre",
          "type": "integer",
          "primaryKey": false,
          "notNull": false
        },
        "disciplina": {
          "name": "disciplina",
          "type": "varchar(100)",
          "primaryKey": false,
          "notNull": false
        },
        "total_aulas": {
          "name": "total_aulas",
          "type": "integer",
          "primaryKey": false,
          "notNull": false,
          "default": 0
        },
        "faltas": {
          "name": "faltas",
          "type": "integer",
          "primaryKey": false,
          "notNull": false,
          "default": 0
        },
        "percentual_frequencia": {
          "name": "percentual_frequencia",
          "type": "numeric(5, 2)",
          "primaryKey": false,
          "notNull": false
        },
        "data_atualizacao": {
          "name": "data_atualizacao",
          "type": "timestamp",
          "primaryKey": false,
          "notNull": false,
          "default": "now()"
        }
      },
      "indexes": {},
      "foreignKeys": {
        "presencas_aluno_id_alunos_id_fk": {
          "name": "presencas_aluno_id_alunos_id_fk",
          "tableFrom": "presencas",
          "tableTo": "alunos",
          "schemaTo": "public",
          "columnsFrom": [
            "aluno_id"
          ],
          "columnsTo": [
            "id"
          ],
          "onDelete": "no action",
          "onUpdate": "no action"
        }
      },
      "compositePrimaryKeys": {},
      "uniqueConstraints": {},
      "checkConstraints": {},
      "policies": {},
      "isRLSEnabled": false
    },
    "public.arquivo_morto_documentos": {
      "name": "arquivo_morto_documentos",
      "schema": "",
      "columns": {
        "id": {
          "name": "id",
          "type": "serial",
          "primaryKey": true,
          "notNull": true
        },
        "arquivo_morto_id": {
          "name": "arquivo_morto_id",
          "type": "integer",
          "primaryKey": false,
          "notNull": true
        },
        "nome_arquivo": {
          "name": "nome_arquivo",
          "type": "varchar(255)",
          "primaryKey": false,
          "notNull": true
        },
        "object_path": {
          "name": "object_path",
          "type": "text",
          "primaryKey": false,
          "notNull": true
        },
        "content_type": {
          "name": "content_type",
          "type": "varchar(100)",
          "primaryKey": false,
          "notNull": false,
          "default": "'application/pdf'"
        },
        "tamanho_bytes": {
          "name": "tamanho_bytes",
          "type": "integer",
          "primaryKey": false,
          "notNull": false
        },
        "criado_em": {
          "name": "criado_em",
          "type": "timestamp",
          "primaryKey": false,
          "notNull": false,
          "default": "now()"
        }
      },
      "indexes": {},
      "foreignKeys": {
        "arquivo_morto_documentos_arquivo_morto_id_arquivo_morto_id_fk": {
          "name": "arquivo_morto_documentos_arquivo_morto_id_arquivo_morto_id_fk",
          "tableFrom": "arquivo_morto_documentos",
          "tableTo": "arquivo_morto",
          "schemaTo": "public",
          "columnsFrom": [
            "arquivo_morto_id"
          ],
          "columnsTo": [
            "id"
          ],
          "onDelete": "cascade",
          "onUpdate": "no action"
        }
      },
      "compositePrimaryKeys": {},
      "uniqueConstraints": {},
      "checkConstraints": {},
      "policies": {},
      "isRLSEnabled": false
    },
    "public.diario_aulas": {
      "name": "diario_aulas",
      "schema": "",
      "columns": {
        "id": {
          "name": "id",
          "type": "serial",
          "primaryKey": true,
          "notNull": true
        },
        "turma_nome": {
          "name": "turma_nome",
          "type": "varchar(50)",
          "primaryKey": false,
          "notNull": true
        },
        "data": {
          "name": "data",
          "type": "varchar(10)",
          "primaryKey": false,
          "notNull": true
        },
        "numero_aulas": {
          "name": "numero_aulas",
          "type": "integer",
          "primaryKey": false,
          "notNull": false,
          "default": 1
        },
        "conteudo": {
          "name": "conteudo",
          "type": "text",
          "primaryKey": false,
          "notNull": false
        },
        "criado_em": {
          "name": "criado_em",
          "type": "timestamp",
          "primaryKey": false,
          "notNull": false,
          "default": "now()"
        }
      },
      "indexes": {
        "diario_aulas_turma_data_idx": {
          "name": "diario_aulas_turma_data_idx",
          "columns": [
            {
              "expression": "turma_nome",
              "asc": true,
              "nulls": "last",
              "opclass": "text_ops",
              "isExpression": false
            },
            {
              "expression": "data",
              "asc": true,
              "nulls": "last",
              "opclass": "text_ops",
              "isExpression": false
            }
          ],
          "isUnique": true,
          "concurrently": false,
          "method": "btree",
          "with": {}
        }
      },
      "foreignKeys": {},
      "compositePrimaryKeys": {},
      "uniqueConstraints": {},
      "checkConstraints": {},
      "policies": {},
      "isRLSEnabled": false
    },
    "public.diario_presencas": {
      "name": "diario_presencas",
      "schema": "",
      "columns": {
        "id": {
          "name": "id",
          "type": "serial",
          "primaryKey": true,
          "notNull": true
        },
        "aula_id": {
          "name": "aula_id",
          "type": "integer",
          "primaryKey": false,
          "notNull": true
        },
        "aluno_id": {
          "name": "aluno_id",
          "type": "integer",
          "primaryKey": false,
          "notNull": true
        },
        "status": {
          "name": "status",
          "type": "varchar(1)",
          "primaryKey": false,
          "notNull": true,
          "default": "'P'"
        }
      },
      "indexes": {
        "diario_presencas_aula_aluno_idx": {
          "name": "diario_presencas_aula_aluno_idx",
          "columns": [
            {
              "expression": "aula_id",
              "asc": true,
              "nulls": "last",
              "opclass": "int4_ops",
              "isExpression": false
            },
            {
              "expression": "aluno_id",
              "asc": true,
              "nulls": "last",
              "opclass": "int4_ops",
              "isExpression": false
            }
          ],
          "isUnique": true,
          "concurrently": false,
          "method": "btree",
          "with": {}
        }
      },
      "foreignKeys": {
        "diario_presencas_aula_id_diario_aulas_id_fk": {
          "name": "diario_presencas_aula_id_diario_aulas_id_fk",
          "tableFrom": "diario_presencas",
          "tableTo": "diario_aulas",
          "schemaTo": "public",
          "columnsFrom": [
            "aula_id"
          ],
          "columnsTo": [
            "id"
          ],
          "onDelete": "cascade",
          "onUpdate": "no action"
        }
      },
      "compositePrimaryKeys": {},
      "uniqueConstraints": {},
      "checkConstraints": {},
      "policies": {},
      "isRLSEnabled": false
    }
  },
  "enums": {},
  "schemas": {},
  "sequences": {},
  "roles": {},
  "policies": {},
  "views": {},
  "_meta": {
    "schemas": {},
    "tables": {},
    "columns": {}
  },
  "internal": {
    "tables": {}
  }
}